sourcehut/__init__.py
sourcehut/_utils.py
sourcehut/client.py
sourcehut/config.py
sourcehut/exceptions.py
sourcehut/py.typed
sourcehut/services/__init__.py
sourcehut/services/_base.py
sourcehut/services/builds.py
sourcehut/services/git.py
sourcehut/services/lists.py
sourcehut/services/meta.py
sourcehut/services/pages.py
sourcehut/services/paste.py
sourcehut/services/todo.py
sourcehutx-0.3.0.dist-info/METADATA
sourcehutx-0.3.0.dist-info/WHEEL
sourcehutx-0.3.0.dist-info/licenses/LICENSE
sourcehutx-0.3.0.dist-info/RECORD
