Metadata-Version: 2.1
Name: sourcehutx
Version: 0.3.0
Summary: Async Python client for the Sourcehut API
Project-URL: Source, https://git.sr.ht/~gotmax23/sourcehutx
Project-URL: Mailing List, https://lists.sr.ht/~gotmax23/sourcehutx
Project-URL: Changelog, https://git.sr.ht/~gotmax23/sourcehutx/tree/main/item/NEWS.md
Author-email: Maxwell G <maxwell@gtmx.me>
License: MIT AND Unlicense
License-File: LICENSE
Classifier: Development Status :: 3 - Alpha
Classifier: License :: OSI Approved :: MIT License
Classifier: Programming Language :: Python :: 3
Classifier: Programming Language :: Python :: 3 :: Only
Classifier: Programming Language :: Python :: 3.8
Classifier: Programming Language :: Python :: 3.9
Classifier: Programming Language :: Python :: 3.10
Classifier: Programming Language :: Python :: 3.11
Classifier: Programming Language :: Python :: 3.12
Classifier: Typing :: Typed
Requires-Python: >=3.8
Requires-Dist: httpx
Requires-Dist: pydantic<3,>=1.10
Requires-Dist: tomli; python_version < '3.11'
Provides-Extra: codeqa
Requires-Dist: reuse; extra == 'codeqa'
Requires-Dist: ruff; extra == 'codeqa'
Provides-Extra: dev
Requires-Dist: nox; extra == 'dev'
Requires-Dist: sourcehutx[formatters]; extra == 'dev'
Requires-Dist: sourcehutx[test]; extra == 'dev'
Requires-Dist: sourcehutx[typing]; extra == 'dev'
Provides-Extra: formatters
Requires-Dist: black; extra == 'formatters'
Requires-Dist: isort; extra == 'formatters'
Provides-Extra: test
Requires-Dist: pytest; extra == 'test'
Requires-Dist: pytest-asyncio; extra == 'test'
Requires-Dist: respx; extra == 'test'
Requires-Dist: vcrpy; extra == 'test'
Provides-Extra: typing
Requires-Dist: mypy; extra == 'typing'
Requires-Dist: nox; extra == 'typing'
Requires-Dist: pytest; extra == 'typing'
Requires-Dist: pytest-asyncio; extra == 'typing'
Requires-Dist: respx; extra == 'typing'
Requires-Dist: typing-extensions; extra == 'typing'
